copydocs/__init__.py
copydocs/py.typed
copydocs-0.0.0.dist-info/LICENSE
copydocs-0.0.0.dist-info/METADATA
copydocs-0.0.0.dist-info/WHEEL
copydocs-0.0.0.dist-info/RECORD
