Metadata-Version: 2.1
Name: copydocs
Version: 0.0.0
Summary: DRY: Reuse your docstrings.
License: MIT
Author: bswck
Author-email: bswck.dev@gmail.com
Requires-Python: >=3.8,<4.0
Classifier: License :: OSI Approved :: MIT License
Classifier: Programming Language :: Python :: 3
Classifier: Programming Language :: Python :: 3.8
Classifier: Programming Language :: Python :: 3.9
Classifier: Programming Language :: Python :: 3.10
Classifier: Programming Language :: Python :: 3.11
Classifier: Programming Language :: Python :: 3.12
